aeon_ancestry/__init__.py
aeon_ancestry/aeon.py
aeon_ancestry/estimatorModels.py
aeon_ancestry/genotype_from_vcf.py
aeon_ancestry/refs/__init__.py
aeon_ancestry/refs/g1k_PCA_centres.csv
aeon_ancestry/refs/g1k_PCA_rotations.csv
aeon_ancestry/refs/g1k_PCA_scale_factors.csv
aeon_ancestry/refs/g1k_allele_freqs.txt
aeon_ancestry/refs/pop2super.txt
aeon_ancestry/refs/reference_PC3s.txt
aeon_ancestry/util.py
aeon_ancestry/visualisePCA.py
aeon_ancestry-1.0.2.dist-info/LICENSE
aeon_ancestry-1.0.2.dist-info/METADATA
aeon_ancestry-1.0.2.dist-info/WHEEL
aeon_ancestry-1.0.2.dist-info/entry_points.txt
aeon_ancestry-1.0.2.dist-info/RECORD
