Metadata-Version: 2.3
Name: aeon-ancestry
Version: 1.0.2
Summary: AEon performs global genetic Ancestry Estimation from genome-wide SNPs
Author: Naomi Warren
Author-email: warren.naomi.m@gmail.com
Requires-Python: >=3.10, <3.13
Classifier: Programming Language :: Python :: 3
Classifier: Programming Language :: Python :: 3.10
Classifier: Programming Language :: Python :: 3.11
Classifier: Programming Language :: Python :: 3.12
Requires-Dist: colorama (>=0.4.6,<0.5.0)
Requires-Dist: matplotlib (==3.8.0)
Requires-Dist: mypy (>=1.14.1,<2.0.0)
Requires-Dist: pandas (>=2.2.3,<3.0.0)
Requires-Dist: pandas-stubs (>=2.2.3.241126,<3.0.0.0)
Requires-Dist: pyro-api (>=0.1.2,<0.2.0)
Requires-Dist: pyro-ppl (>=1.9.1,<2.0.0)
Requires-Dist: pysam (>=0.22.1,<0.23.0)
Requires-Dist: torch (>=2.5.1,<3.0.0)
Requires-Dist: types-colorama (>=0.4.15.20240311,<0.5.0.0)
